synapyse/__init__.py
synapyse/base/connection.py
synapyse/base/layer.py
synapyse/base/neural_network.py
synapyse/base/neuron.py
synapyse/base/__init__.py
synapyse/base/activation_functions/activation_function.py
synapyse/base/activation_functions/__init__.py
synapyse/base/input_functions/input_function.py
synapyse/base/input_functions/__init__.py
synapyse/base/learning/iterative_learning.py
synapyse/base/learning/learning_method.py
synapyse/base/learning/supervised_learning.py
synapyse/base/learning/training_set.py
synapyse/base/learning/unsupervised_learning.py
synapyse/base/learning/__init__.py
synapyse/base/learning/error_functions/error_function.py
synapyse/base/learning/error_functions/__init__.py
synapyse/impl/bias_neuron.py
synapyse/impl/hopfield.py
synapyse/impl/hopfield_layer.py
synapyse/impl/input_output_neuron.py
synapyse/impl/multi_layer_perceptron.py
synapyse/impl/perceptron.py
synapyse/impl/__init__.py
synapyse/impl/activation_functions/linear.py
synapyse/impl/activation_functions/sigmoid.py
synapyse/impl/activation_functions/step.py
synapyse/impl/activation_functions/tanh.py
synapyse/impl/activation_functions/__init__.py
synapyse/impl/input_functions/weighted_sum.py
synapyse/impl/input_functions/__init__.py
synapyse/impl/learning/back_propagation.py
synapyse/impl/learning/binary_hebbian_learning.py
synapyse/impl/learning/least_mean_square.py
synapyse/impl/learning/momentum_back_propagation.py
synapyse/impl/learning/unsupervised_hebbian_learning.py
synapyse/impl/learning/__init__.py
synapyse/impl/learning/error_functions/rms.py
synapyse/impl/learning/error_functions/__init__.py
synapyse/samples/__init__.py
synapyse/samples/impl/car_evaluation.py
synapyse/samples/impl/heart_disease.py
synapyse/samples/impl/__init__.py
synapyse/test/__init__.py
synapyse/test/core/neural_network_test.py
synapyse/test/core/__init__.py
synapyse/test/impl/back_propagation_test.py
synapyse/test/impl/back_propagation_test_2.py
synapyse-0.0.2.dist-info/DESCRIPTION.rst
synapyse-0.0.2.dist-info/METADATA
synapyse-0.0.2.dist-info/metadata.json
synapyse-0.0.2.dist-info/RECORD
synapyse-0.0.2.dist-info/top_level.txt
synapyse-0.0.2.dist-info/WHEEL
