Metadata-Version: 2.0
Name: synapyse
Version: 0.0.2
Summary: Just another Artificial Neural Network API
Home-page: https://github.com/synapyse/synapyse
Author: Douglas Eric Fonseca Rodrigues
Author-email: dougefr@gmail.com
License: MIT
